redis_subjects_storage/__init__.py
redis_subjects_storage/storage_impl.py
redis_subjects_storage/test_storage.py
krules_subjects_storage_redis-0.12.0.dist-info/AUTHORS
krules_subjects_storage_redis-0.12.0.dist-info/LICENSE
krules_subjects_storage_redis-0.12.0.dist-info/METADATA
krules_subjects_storage_redis-0.12.0.dist-info/WHEEL
krules_subjects_storage_redis-0.12.0.dist-info/RECORD
